[{"line":1,"elements":[{"start_timestamp":"2024-08-31T18:05:20.223Z","line":10,"name":"Successful login with PAN and password","description":"","id":"login;successful-login-with-pan-and-password;;2","type":"scenario","keyword":"Scenario","steps":[{"result":{"status":"undefined"},"line":3,"name":"the user is on the login page","match":{},"keyword":"Given "},{"result":{"duration":996600,"status":"skipped"},"line":4,"name":"User login into application with \"<PanNumber>\" and password \"Reset@1234\"","match":{},"keyword":"When "},{"result":{"duration":1995700,"status":"skipped"},"line":5,"name":"Click on login button","match":{},"keyword":"And "},{"result":{"duration":1994200,"status":"skipped"},"line":6,"name":"dashboard page should be display","match":{},"keyword":"Then "}]}],"name":"login","description":"","id":"login","keyword":"Feature","uri":"file:src/test/java/features/Login.feature","tags":[]},{"line":1,"elements":[{"line":3,"name":"","description":"","type":"background","keyword":"Background","steps":[{"result":{"status":"undefined"},"line":4,"name":"the investor is logged in","match":{},"keyword":"Given "},{"result":{"status":"skipped"},"line":5,"name":"the dashboard page is displayed","match":{},"keyword":"And "}]},{"start_timestamp":"2024-08-31T18:05:20.490Z","line":7,"name":"Successful login with PAN and password","description":"","id":"investor-login-pms-partial-redemption-for-single-holder;successful-login-with-pan-and-password","type":"scenario","keyword":"Scenario","steps":[{"result":{"duration":1005800,"status":"skipped"},"line":8,"name":"the user is on the login page","match":{},"keyword":"Given "},{"result":{"duration":1003100,"status":"skipped"},"line":9,"name":"the user logs into the application with \"<PanNumber>\" and password \"Reset@1234\"","match":{},"keyword":"When "},{"result":{"duration":997700,"status":"skipped"},"line":10,"name":"the user clicks on the login button","match":{},"keyword":"And "},{"result":{"duration":995800,"status":"skipped"},"line":11,"name":"the dashboard page should be displayed","match":{},"keyword":"Then "}]},{"line":3,"name":"","description":"","type":"background","keyword":"Background","steps":[{"result":{"status":"undefined"},"line":4,"name":"the investor is logged in","match":{},"keyword":"Given "},{"result":{"duration":997900,"status":"skipped"},"line":5,"name":"the dashboard page is displayed","match":{},"keyword":"And "}]},{"start_timestamp":"2024-08-31T18:05:20.541Z","line":13,"name":"Investor navigates to the redemption page","description":"","id":"investor-login-pms-partial-redemption-for-single-holder;investor-navigates-to-the-redemption-page","type":"scenario","keyword":"Scenario","steps":[{"result":{"status":"skipped"},"line":14,"name":"the investor clicks on the Redemption Module from the side menu","match":{},"keyword":"When "},{"result":{"duration":998500,"status":"skipped"},"line":15,"name":"the PMS Redemption page should be displayed on the screen","match":{},"keyword":"Then "}]},{"line":3,"name":"","description":"","type":"background","keyword":"Background","steps":[{"result":{"status":"undefined"},"line":4,"name":"the investor is logged in","match":{},"keyword":"Given "},{"result":{"duration":996000,"status":"skipped"},"line":5,"name":"the dashboard page is displayed","match":{},"keyword":"And "}]},{"start_timestamp":"2024-08-31T18:05:20.574Z","line":17,"name":"Investor selects PMS redemption option","description":"","id":"investor-login-pms-partial-redemption-for-single-holder;investor-selects-pms-redemption-option","type":"scenario","keyword":"Scenario","steps":[{"result":{"duration":995700,"status":"skipped"},"line":18,"name":"the investor is on the redemption page","match":{},"keyword":"Given "},{"result":{"status":"skipped"},"line":19,"name":"the investor selects \"Single Holder\" from the dropdown","match":{},"keyword":"When "},{"result":{"status":"skipped"},"line":20,"name":"the investor selects the Strategy checkbox","match":{},"keyword":"And "},{"result":{"duration":995400,"status":"skipped"},"line":21,"name":"the investor clicks on the Partial radio button","match":{},"keyword":"And "}]},{"line":3,"name":"","description":"","type":"background","keyword":"Background","steps":[{"result":{"status":"undefined"},"line":4,"name":"the investor is logged in","match":{},"keyword":"Given "},{"result":{"duration":995400,"status":"skipped"},"line":5,"name":"the dashboard page is displayed","match":{},"keyword":"And "}]},{"start_timestamp":"2024-08-31T18:05:20.612Z","line":23,"name":"Investor enters invalid and valid amounts and verifies error validation messages","description":"","id":"investor-login-pms-partial-redemption-for-single-holder;investor-enters-invalid-and-valid-amounts-and-verifies-error-validation-messages","type":"scenario","keyword":"Scenario","steps":[{"result":{"status":"skipped"},"line":24,"name":"the investor is on the redemption page","match":{},"keyword":"Given "},{"result":{"duration":997700,"status":"skipped"},"line":25,"name":"the investor enters an amount less than 2 Lakhs in the amount field","match":{},"keyword":"When "},{"result":{"status":"skipped"},"line":26,"name":"the investor should see a validation message for the minimum amount requirement","match":{},"keyword":"Then "},{"result":{"duration":998500,"status":"skipped"},"line":27,"name":"the investor enters an amount equal to the AUM amount","match":{},"keyword":"When "},{"result":{"duration":997100,"status":"skipped"},"line":28,"name":"the investor should see a validation message for the maximum amount","match":{},"keyword":"Then "},{"result":{"status":"skipped"},"line":29,"name":"the investor does not enter an amount and clicks on the redeem button","match":{},"keyword":"When "},{"result":{"status":"skipped"},"line":30,"name":"the redeem button should be disabled","match":{},"keyword":"Then "}]},{"line":3,"name":"","description":"","type":"background","keyword":"Background","steps":[{"result":{"status":"undefined"},"line":4,"name":"the investor is logged in","match":{},"keyword":"Given "},{"result":{"duration":997500,"status":"skipped"},"line":5,"name":"the dashboard page is displayed","match":{},"keyword":"And "}]},{"start_timestamp":"2024-08-31T18:05:20.650Z","line":32,"name":"Investor redeems investment and verifies details","description":"","id":"investor-login-pms-partial-redemption-for-single-holder;investor-redeems-investment-and-verifies-details","type":"scenario","keyword":"Scenario","steps":[{"result":{"duration":1002600,"status":"skipped"},"line":33,"name":"the investor is on the redemption page","match":{},"keyword":"Given "},{"result":{"duration":996700,"status":"skipped"},"line":34,"name":"the L2 screen is displayed","match":{},"keyword":"When "},{"result":{"status":"skipped"},"line":35,"name":"the entered amount is displayed on the L2 screen","match":{},"keyword":"And "},{"result":{"status":"skipped"},"line":36,"name":"the investor clicks on the T&C checkbox and clicks on the redeem amount button","match":{},"keyword":"And "},{"result":{"status":"skipped"},"line":37,"name":"the investor enters the OTP","match":{},"keyword":"And "},{"result":{"status":"skipped"},"line":38,"name":"the investor should see a success validation message","match":{},"keyword":"Then "}]},{"line":3,"name":"","description":"","type":"background","keyword":"Background","steps":[{"result":{"status":"undefined"},"line":4,"name":"the investor is logged in","match":{},"keyword":"Given "},{"result":{"duration":997100,"status":"skipped"},"line":5,"name":"the dashboard page is displayed","match":{},"keyword":"And "}]},{"start_timestamp":"2024-08-31T18:05:20.684Z","line":40,"name":"Investor verifies transaction in recent transactions page","description":"","id":"investor-login-pms-partial-redemption-for-single-holder;investor-verifies-transaction-in-recent-transactions-page","type":"scenario","keyword":"Scenario","steps":[{"result":{"duration":997400,"status":"skipped"},"line":41,"name":"the investor is on the dashboard page","match":{},"keyword":"Given "},{"result":{"duration":996500,"status":"skipped"},"line":42,"name":"the investor clicks on the recent transaction option from the side menu","match":{},"keyword":"When "},{"result":{"duration":997200,"status":"skipped"},"line":43,"name":"the investor should see the entry in the transaction list","match":{},"keyword":"Then "},{"result":{"duration":998700,"status":"skipped"},"line":44,"name":"the status of the transaction should be displayed correctly","match":{},"keyword":"And "}]}],"name":"Investor Login PMS Partial Redemption for Single Holder","description":"","id":"investor-login-pms-partial-redemption-for-single-holder","keyword":"Feature","uri":"file:src/test/java/features/PMSPartialRedemptionSingleHolder_InvestorLogin.feature","tags":[]}]